
    
    [{"author":"IT Meets World","categories":null,"contents":"A blog about the things I\u0026rsquo;ve discovered and currently discovering in the world of IT. I have 5+ years of experience in this world and I thought I create a means of presenting everything I\u0026rsquo;ve learned so far. Join my madness, as I learn new skills either in or outside the world of IT.","date":"2023-02-01T00:00:00Z","permalink":"https://itmeetsworld.com/page/about/","tags":null,"title":"About Me"},{"author":"IT Meeets World","categories":null,"contents":"","date":"2023-02-01T00:00:00Z","permalink":"https://itmeetsworld.com/blog/20230131-hello-world/","tags":["hello"],"title":"Hello, World!"}]